opper_agents/__init__.py
opper_agents/agents/__init__.py
opper_agents/agents/chat.py
opper_agents/agents/react.py
opper_agents/base/__init__.py
opper_agents/base/agent.py
opper_agents/base/context.py
opper_agents/base/hooks.py
opper_agents/base/tool.py
opper_agents/core/__init__.py
opper_agents/core/agent.py
opper_agents/core/schemas.py
opper_agents/mcp/__init__.py
opper_agents/mcp/client.py
opper_agents/mcp/config.py
opper_agents/mcp/custom_sse.py
opper_agents/mcp/provider.py
opper_agents/memory/__init__.py
opper_agents/memory/memory.py
opper_agents/utils/__init__.py
opper_agents/utils/decorators.py
opper_agents/utils/logging.py
opper_agents/utils/version.py
opper_agents/py.typed
opper_agents-0.3.0.dist-info/METADATA
opper_agents-0.3.0.dist-info/WHEEL
opper_agents-0.3.0.dist-info/entry_points.txt
opper_agents-0.3.0.dist-info/RECORD
