Metadata-Version: 2.4
Name: opper-agents
Version: 0.3.0
Summary: Opper-based agent workflows SDK
Author: Opper
License: MIT
Requires-Python: >=3.11
Requires-Dist: mcp>=1.14.0
Requires-Dist: opperai>=1.2.1
Requires-Dist: pydantic>=2.6.0
Requires-Dist: pytest-asyncio>=1.1.0
Requires-Dist: rich>=13.7.0
Requires-Dist: typing-extensions>=4.9.0
Provides-Extra: composio
Requires-Dist: composio>=0.5.0; extra == 'composio'
Provides-Extra: dev
Requires-Dist: coverage>=7.0.0; extra == 'dev'
Requires-Dist: mypy>=1.0.0; extra == 'dev'
Requires-Dist: pytest-asyncio>=0.21.0; extra == 'dev'
Requires-Dist: pytest-cov>=4.0.0; extra == 'dev'
Requires-Dist: pytest-mock>=3.10.0; extra == 'dev'
Requires-Dist: pytest-xdist>=3.0.0; extra == 'dev'
Requires-Dist: pytest>=7.0.0; extra == 'dev'
Requires-Dist: ruff>=0.14.0; extra == 'dev'
Requires-Dist: vcrpy==7.0.0; extra == 'dev'
Provides-Extra: mcp
Requires-Dist: aiohttp>=3.8.0; extra == 'mcp'
